configparser_utils/__init__.py
configparser_utils/configutils.py
configparser_utils-0.1.1.dist-info/LICENSE
configparser_utils-0.1.1.dist-info/METADATA
configparser_utils-0.1.1.dist-info/WHEEL
configparser_utils-0.1.1.dist-info/top_level.txt
configparser_utils-0.1.1.dist-info/RECORD
