Metadata-Version: 2.1
Name: configparser-utils
Version: 0.1.1
Summary: Simple utilities to handle files with configparser
Home-page: https://github.com/ku-dmitry/configparser-utils
Author: Dmitry Kupriyanov
License: UNKNOWN
Project-URL: Bug Tracker, https://github.com/ku-dmitry/configparser-utils/issues
Platform: UNKNOWN
Classifier: Programming Language :: Python :: 3
Classifier: License :: OSI Approved :: MIT License
Classifier: Operating System :: OS Independent
Requires-Python: >=3.6
License-File: LICENSE
